setup.cfg
setup.py
turbosmsua/__init__.py
turbosmsua.egg-info/PKG-INFO
turbosmsua.egg-info/SOURCES.txt
turbosmsua.egg-info/dependency_links.txt
turbosmsua.egg-info/requires.txt
turbosmsua.egg-info/top_level.txt