Metadata-Version: 1.1
Name: turbosmsua
Version: 0.3
Summary: Client for https://turbosms.ua
Home-page: https://github.com/Krokop/turbosmsua
Author: Serbokryl Oleg
Author-email: chezar1995@gmail.com
License: UNKNOWN
Download-URL: https://github.com/Krokop/turbosmsua/tarball/0.3
Keywords: turbosmsua,turbosms,sms ua
Platform: UNKNOWN
